geomfig/__init__.py
geomfig/base.py
geomfig/circle.py
geomfig/triangle.py
geomfig-0.1.0.dist-info/licenses/LICENSE
geomfig-0.1.0.dist-info/METADATA
geomfig-0.1.0.dist-info/WHEEL
geomfig-0.1.0.dist-info/top_level.txt
geomfig-0.1.0.dist-info/RECORD
