Metadata-Version: 2.4
Name: geomfig
Version: 0.1.0
Summary: Библиотека для подсчёта площади геометрических фигур
License: MIT
Project-URL: Homepage, https://github.com/ChudoYuda/geomfig.git
Project-URL: Source Code, https://github.com/ChudoYuda/geomfig.git
Requires-Python: >=3.12
License-File: LICENSE
Provides-Extra: dev
Requires-Dist: pytest>=8.4.2; extra == "dev"
Dynamic: license-file
